multiples/__init__.py
multiples/is_multiple_of_five.py
multiples/is_multiple_of_two.py
multiples/module1.py
multiples/module2.py
tests/__init__.py
tests/test_is_multiple_of_five.py
tests/test_is_multiple_of_two.py
abble_multiples-0.1.0.dist-info/METADATA
abble_multiples-0.1.0.dist-info/WHEEL
abble_multiples-0.1.0.dist-info/top_level.txt
abble_multiples-0.1.0.dist-info/RECORD
