Metadata-Version: 2.4
Name: abble_multiples
Version: 0.1.0
Summary: 一个用于检查2和5倍数的库。
Author: Abble
Author-email: 17317591875@163.com
Classifier: Programming Language :: Python :: 3
Classifier: License :: OSI Approved :: MIT License
Classifier: Operating System :: OS Independent
Requires-Python: >=3.6
Dynamic: author
Dynamic: author-email
Dynamic: classifier
Dynamic: requires-python
Dynamic: summary
